{"metadata": {"dbt_schema_version": "https://schemas.getdbt.com/dbt/catalog/v1.json", "dbt_version": "1.8.9", "generated_at": "2025-04-03T07:35:18.956431Z", "invocation_id": "d9255e16-b616-4b05-9ce9-e38014d947dc", "env": {}}, "nodes": {"model.elementary.data_monitoring_metrics": {"metadata": {"type": "BASE TABLE", "schema": "elementary", "name": "data_monitoring_metrics", "database": "remitpro", "comment": null, "owner": "dbo"}, "columns": {"id": {"type": "varchar", "index": 1, "name": "id", "comment": null}, "full_table_name": {"type": "varchar", "index": 2, "name": "full_table_name", "comment": null}, "column_name": {"type": "varchar", "index": 3, "name": "column_name", "comment": null}, "metric_name": {"type": "varchar", "index": 4, "name": "metric_name", "comment": null}, "metric_value": {"type": "float", "index": 5, "name": "metric_value", "comment": null}, "source_value": {"type": "varchar", "index": 6, "name": "source_value", "comment": null}, "bucket_start": {"type": "datetime2", "index": 7, "name": "bucket_start", "comment": null}, "bucket_end": {"type": "datetime2", "index": 8, "name": "bucket_end", "comment": null}, "bucket_duration_hours": {"type": "int", "index": 9, "name": "bucket_duration_hours", "comment": null}, "updated_at": {"type": "datetime2", "index": 10, "name": "updated_at", "comment": null}, "dimension": {"type": "varchar", "index": 11, "name": "dimension", "comment": null}, "dimension_value": {"type": "varchar", "index": 12, "name": "dimension_value", "comment": null}, "metric_properties": {"type": "varchar", "index": 13, "name": "metric_properties", "comment": null}, "created_at": {"type": "datetime2", "index": 14, "name": "created_at", "comment": null}}, "stats": {"has_stats": {"id": "has_stats", "label": "Has Stats?", "value": false, "include": false, "description": "Indicates whether there are statistics for this table"}}, "unique_id": "model.elementary.data_monitoring_metrics"}, "model.elementary.dbt_columns": {"metadata": {"type": "BASE TABLE", "schema": "elementary", "name": "dbt_columns", "database": "remitpro", "comment": null, "owner": "dbo"}, "columns": {"unique_id": {"type": "varchar", "index": 1, "name": "unique_id", "comment": null}, "parent_unique_id": {"type": "varchar", "index": 2, "name": "parent_unique_id", "comment": null}, "name": {"type": "varchar", "index": 3, "name": "name", "comment": null}, "data_type": {"type": "varchar", "index": 4, "name": "data_type", "comment": null}, "tags": {"type": "varchar", "index": 5, "name": "tags", "comment": null}, "meta": {"type": "varchar", "index": 6, "name": "meta", "comment": null}, "database_name": {"type": "varchar", "index": 7, "name": "database_name", "comment": null}, "schema_name": {"type": "varchar", "index": 8, "name": "schema_name", "comment": null}, "table_name": {"type": "varchar", "index": 9, "name": "table_name", "comment": null}, "description": {"type": "varchar", "index": 10, "name": "description", "comment": null}, "resource_type": {"type": "varchar", "index": 11, "name": "resource_type", "comment": null}, "generated_at": {"type": "varchar", "index": 12, "name": "generated_at", "comment": null}, "metadata_hash": {"type": "varchar", "index": 13, "name": "metadata_hash", "comment": null}}, "stats": {"has_stats": {"id": "has_stats", "label": "Has Stats?", "value": false, "include": false, "description": "Indicates whether there are statistics for this table"}}, "unique_id": "model.elementary.dbt_columns"}, "model.elementary.dbt_exposures": {"metadata": {"type": "BASE TABLE", "schema": "elementary", "name": "dbt_exposures", "database": "remitpro", "comment": null, "owner": "dbo"}, "columns": {"unique_id": {"type": "varchar", "index": 1, "name": "unique_id", "comment": null}, "name": {"type": "varchar", "index": 2, "name": "name", "comment": null}, "maturity": {"type": "varchar", "index": 3, "name": "maturity", "comment": null}, "type": {"type": "varchar", "index": 4, "name": "type", "comment": null}, "owner_email": {"type": "varchar", "index": 5, "name": "owner_email", "comment": null}, "owner_name": {"type": "varchar", "index": 6, "name": "owner_name", "comment": null}, "url": {"type": "varchar", "index": 7, "name": "url", "comment": null}, "depends_on_macros": {"type": "varchar", "index": 8, "name": "depends_on_macros", "comment": null}, "depends_on_nodes": {"type": "varchar", "index": 9, "name": "depends_on_nodes", "comment": null}, "description": {"type": "varchar", "index": 10, "name": "description", "comment": null}, "tags": {"type": "varchar", "index": 11, "name": "tags", "comment": null}, "meta": {"type": "varchar", "index": 12, "name": "meta", "comment": null}, "package_name": {"type": "varchar", "index": 13, "name": "package_name", "comment": null}, "original_path": {"type": "varchar", "index": 14, "name": "original_path", "comment": null}, "path": {"type": "varchar", "index": 15, "name": "path", "comment": null}, "generated_at": {"type": "varchar", "index": 16, "name": "generated_at", "comment": null}, "metadata_hash": {"type": "varchar", "index": 17, "name": "metadata_hash", "comment": null}, "label": {"type": "varchar", "index": 18, "name": "label", "comment": null}, "raw_queries": {"type": "varchar", "index": 19, "name": "raw_queries", "comment": null}}, "stats": {"has_stats": {"id": "has_stats", "label": "Has Stats?", "value": false, "include": false, "description": "Indicates whether there are statistics for this table"}}, "unique_id": "model.elementary.dbt_exposures"}, "model.elementary.dbt_metrics": {"metadata": {"type": "BASE TABLE", "schema": "elementary", "name": "dbt_metrics", "database": "remitpro", "comment": null, "owner": "dbo"}, "columns": {"unique_id": {"type": "varchar", "index": 1, "name": "unique_id", "comment": null}, "name": {"type": "varchar", "index": 2, "name": "name", "comment": null}, "label": {"type": "varchar", "index": 3, "name": "label", "comment": null}, "model": {"type": "varchar", "index": 4, "name": "model", "comment": null}, "type": {"type": "varchar", "index": 5, "name": "type", "comment": null}, "sql": {"type": "varchar", "index": 6, "name": "sql", "comment": null}, "timestamp": {"type": "varchar", "index": 7, "name": "timestamp", "comment": null}, "filters": {"type": "varchar", "index": 8, "name": "filters", "comment": null}, "time_grains": {"type": "varchar", "index": 9, "name": "time_grains", "comment": null}, "dimensions": {"type": "varchar", "index": 10, "name": "dimensions", "comment": null}, "depends_on_macros": {"type": "varchar", "index": 11, "name": "depends_on_macros", "comment": null}, "depends_on_nodes": {"type": "varchar", "index": 12, "name": "depends_on_nodes", "comment": null}, "description": {"type": "varchar", "index": 13, "name": "description", "comment": null}, "tags": {"type": "varchar", "index": 14, "name": "tags", "comment": null}, "meta": {"type": "varchar", "index": 15, "name": "meta", "comment": null}, "package_name": {"type": "varchar", "index": 16, "name": "package_name", "comment": null}, "original_path": {"type": "varchar", "index": 17, "name": "original_path", "comment": null}, "path": {"type": "varchar", "index": 18, "name": "path", "comment": null}, "generated_at": {"type": "varchar", "index": 19, "name": "generated_at", "comment": null}, "metadata_hash": {"type": "varchar", "index": 20, "name": "metadata_hash", "comment": null}}, "stats": {"has_stats": {"id": "has_stats", "label": "Has Stats?", "value": false, "include": false, "description": "Indicates whether there are statistics for this table"}}, "unique_id": "model.elementary.dbt_metrics"}, "model.elementary.dbt_models": {"metadata": {"type": "BASE TABLE", "schema": "elementary", "name": "dbt_models", "database": "remitpro", "comment": null, "owner": "dbo"}, "columns": {"unique_id": {"type": "varchar", "index": 1, "name": "unique_id", "comment": null}, "alias": {"type": "varchar", "index": 2, "name": "alias", "comment": null}, "checksum": {"type": "varchar", "index": 3, "name": "checksum", "comment": null}, "materialization": {"type": "varchar", "index": 4, "name": "materialization", "comment": null}, "tags": {"type": "varchar", "index": 5, "name": "tags", "comment": null}, "meta": {"type": "varchar", "index": 6, "name": "meta", "comment": null}, "owner": {"type": "varchar", "index": 7, "name": "owner", "comment": null}, "database_name": {"type": "varchar", "index": 8, "name": "database_name", "comment": null}, "schema_name": {"type": "varchar", "index": 9, "name": "schema_name", "comment": null}, "depends_on_macros": {"type": "varchar", "index": 10, "name": "depends_on_macros", "comment": null}, "depends_on_nodes": {"type": "varchar", "index": 11, "name": "depends_on_nodes", "comment": null}, "description": {"type": "varchar", "index": 12, "name": "description", "comment": null}, "name": {"type": "varchar", "index": 13, "name": "name", "comment": null}, "package_name": {"type": "varchar", "index": 14, "name": "package_name", "comment": null}, "original_path": {"type": "varchar", "index": 15, "name": "original_path", "comment": null}, "path": {"type": "varchar", "index": 16, "name": "path", "comment": null}, "patch_path": {"type": "varchar", "index": 17, "name": "patch_path", "comment": null}, "generated_at": {"type": "varchar", "index": 18, "name": "generated_at", "comment": null}, "metadata_hash": {"type": "varchar", "index": 19, "name": "metadata_hash", "comment": null}}, "stats": {"has_stats": {"id": "has_stats", "label": "Has Stats?", "value": false, "include": false, "description": "Indicates whether there are statistics for this table"}}, "unique_id": "model.elementary.dbt_models"}, "model.elementary.dbt_seeds": {"metadata": {"type": "BASE TABLE", "schema": "elementary", "name": "dbt_seeds", "database": "remitpro", "comment": null, "owner": "dbo"}, "columns": {"unique_id": {"type": "varchar", "index": 1, "name": "unique_id", "comment": null}, "alias": {"type": "varchar", "index": 2, "name": "alias", "comment": null}, "checksum": {"type": "varchar", "index": 3, "name": "checksum", "comment": null}, "tags": {"type": "varchar", "index": 4, "name": "tags", "comment": null}, "meta": {"type": "varchar", "index": 5, "name": "meta", "comment": null}, "owner": {"type": "varchar", "index": 6, "name": "owner", "comment": null}, "database_name": {"type": "varchar", "index": 7, "name": "database_name", "comment": null}, "schema_name": {"type": "varchar", "index": 8, "name": "schema_name", "comment": null}, "description": {"type": "varchar", "index": 9, "name": "description", "comment": null}, "name": {"type": "varchar", "index": 10, "name": "name", "comment": null}, "package_name": {"type": "varchar", "index": 11, "name": "package_name", "comment": null}, "original_path": {"type": "varchar", "index": 12, "name": "original_path", "comment": null}, "path": {"type": "varchar", "index": 13, "name": "path", "comment": null}, "generated_at": {"type": "varchar", "index": 14, "name": "generated_at", "comment": null}, "metadata_hash": {"type": "varchar", "index": 15, "name": "metadata_hash", "comment": null}}, "stats": {"has_stats": {"id": "has_stats", "label": "Has Stats?", "value": false, "include": false, "description": "Indicates whether there are statistics for this table"}}, "unique_id": "model.elementary.dbt_seeds"}, "model.elementary.dbt_snapshots": {"metadata": {"type": "BASE TABLE", "schema": "elementary", "name": "dbt_snapshots", "database": "remitpro", "comment": null, "owner": "dbo"}, "columns": {"unique_id": {"type": "varchar", "index": 1, "name": "unique_id", "comment": null}, "alias": {"type": "varchar", "index": 2, "name": "alias", "comment": null}, "checksum": {"type": "varchar", "index": 3, "name": "checksum", "comment": null}, "materialization": {"type": "varchar", "index": 4, "name": "materialization", "comment": null}, "tags": {"type": "varchar", "index": 5, "name": "tags", "comment": null}, "meta": {"type": "varchar", "index": 6, "name": "meta", "comment": null}, "owner": {"type": "varchar", "index": 7, "name": "owner", "comment": null}, "database_name": {"type": "varchar", "index": 8, "name": "database_name", "comment": null}, "schema_name": {"type": "varchar", "index": 9, "name": "schema_name", "comment": null}, "depends_on_macros": {"type": "varchar", "index": 10, "name": "depends_on_macros", "comment": null}, "depends_on_nodes": {"type": "varchar", "index": 11, "name": "depends_on_nodes", "comment": null}, "description": {"type": "varchar", "index": 12, "name": "description", "comment": null}, "name": {"type": "varchar", "index": 13, "name": "name", "comment": null}, "package_name": {"type": "varchar", "index": 14, "name": "package_name", "comment": null}, "original_path": {"type": "varchar", "index": 15, "name": "original_path", "comment": null}, "path": {"type": "varchar", "index": 16, "name": "path", "comment": null}, "patch_path": {"type": "varchar", "index": 17, "name": "patch_path", "comment": null}, "generated_at": {"type": "varchar", "index": 18, "name": "generated_at", "comment": null}, "metadata_hash": {"type": "varchar", "index": 19, "name": "metadata_hash", "comment": null}}, "stats": {"has_stats": {"id": "has_stats", "label": "Has Stats?", "value": false, "include": false, "description": "Indicates whether there are statistics for this table"}}, "unique_id": "model.elementary.dbt_snapshots"}, "model.elementary.dbt_source_freshness_results": {"metadata": {"type": "BASE TABLE", "schema": "elementary", "name": "dbt_source_freshness_results", "database": "remitpro", "comment": null, "owner": "dbo"}, "columns": {"source_freshness_execution_id": {"type": "varchar", "index": 1, "name": "source_freshness_execution_id", "comment": null}, "unique_id": {"type": "varchar", "index": 2, "name": "unique_id", "comment": null}, "max_loaded_at": {"type": "varchar", "index": 3, "name": "max_loaded_at", "comment": null}, "snapshotted_at": {"type": "varchar", "index": 4, "name": "snapshotted_at", "comment": null}, "generated_at": {"type": "varchar", "index": 5, "name": "generated_at", "comment": null}, "created_at": {"type": "datetime2", "index": 6, "name": "created_at", "comment": null}, "max_loaded_at_time_ago_in_s": {"type": "float", "index": 7, "name": "max_loaded_at_time_ago_in_s", "comment": null}, "status": {"type": "varchar", "index": 8, "name": "status", "comment": null}, "error": {"type": "varchar", "index": 9, "name": "error", "comment": null}, "compile_started_at": {"type": "varchar", "index": 10, "name": "compile_started_at", "comment": null}, "compile_completed_at": {"type": "varchar", "index": 11, "name": "compile_completed_at", "comment": null}, "execute_started_at": {"type": "varchar", "index": 12, "name": "execute_started_at", "comment": null}, "execute_completed_at": {"type": "varchar", "index": 13, "name": "execute_completed_at", "comment": null}, "invocation_id": {"type": "varchar", "index": 14, "name": "invocation_id", "comment": null}, "warn_after": {"type": "varchar", "index": 15, "name": "warn_after", "comment": null}, "error_after": {"type": "varchar", "index": 16, "name": "error_after", "comment": null}, "filter": {"type": "varchar", "index": 17, "name": "filter", "comment": null}}, "stats": {"has_stats": {"id": "has_stats", "label": "Has Stats?", "value": false, "include": false, "description": "Indicates whether there are statistics for this table"}}, "unique_id": "model.elementary.dbt_source_freshness_results"}, "model.elementary.dbt_sources": {"metadata": {"type": "BASE TABLE", "schema": "elementary", "name": "dbt_sources", "database": "remitpro", "comment": null, "owner": "dbo"}, "columns": {"unique_id": {"type": "varchar", "index": 1, "name": "unique_id", "comment": null}, "database_name": {"type": "varchar", "index": 2, "name": "database_name", "comment": null}, "schema_name": {"type": "varchar", "index": 3, "name": "schema_name", "comment": null}, "source_name": {"type": "varchar", "index": 4, "name": "source_name", "comment": null}, "name": {"type": "varchar", "index": 5, "name": "name", "comment": null}, "identifier": {"type": "varchar", "index": 6, "name": "identifier", "comment": null}, "loaded_at_field": {"type": "varchar", "index": 7, "name": "loaded_at_field", "comment": null}, "freshness_warn_after": {"type": "varchar", "index": 8, "name": "freshness_warn_after", "comment": null}, "freshness_error_after": {"type": "varchar", "index": 9, "name": "freshness_error_after", "comment": null}, "freshness_filter": {"type": "varchar", "index": 10, "name": "freshness_filter", "comment": null}, "freshness_description": {"type": "varchar", "index": 11, "name": "freshness_description", "comment": null}, "relation_name": {"type": "varchar", "index": 12, "name": "relation_name", "comment": null}, "tags": {"type": "varchar", "index": 13, "name": "tags", "comment": null}, "meta": {"type": "varchar", "index": 14, "name": "meta", "comment": null}, "owner": {"type": "varchar", "index": 15, "name": "owner", "comment": null}, "package_name": {"type": "varchar", "index": 16, "name": "package_name", "comment": null}, "original_path": {"type": "varchar", "index": 17, "name": "original_path", "comment": null}, "path": {"type": "varchar", "index": 18, "name": "path", "comment": null}, "source_description": {"type": "varchar", "index": 19, "name": "source_description", "comment": null}, "description": {"type": "varchar", "index": 20, "name": "description", "comment": null}, "generated_at": {"type": "varchar", "index": 21, "name": "generated_at", "comment": null}, "metadata_hash": {"type": "varchar", "index": 22, "name": "metadata_hash", "comment": null}}, "stats": {"has_stats": {"id": "has_stats", "label": "Has Stats?", "value": false, "include": false, "description": "Indicates whether there are statistics for this table"}}, "unique_id": "model.elementary.dbt_sources"}, "model.elementary.dbt_tests": {"metadata": {"type": "BASE TABLE", "schema": "elementary", "name": "dbt_tests", "database": "remitpro", "comment": null, "owner": "dbo"}, "columns": {"unique_id": {"type": "varchar", "index": 1, "name": "unique_id", "comment": null}, "database_name": {"type": "varchar", "index": 2, "name": "database_name", "comment": null}, "schema_name": {"type": "varchar", "index": 3, "name": "schema_name", "comment": null}, "name": {"type": "varchar", "index": 4, "name": "name", "comment": null}, "short_name": {"type": "varchar", "index": 5, "name": "short_name", "comment": null}, "alias": {"type": "varchar", "index": 6, "name": "alias", "comment": null}, "test_column_name": {"type": "varchar", "index": 7, "name": "test_column_name", "comment": null}, "severity": {"type": "varchar", "index": 8, "name": "severity", "comment": null}, "warn_if": {"type": "varchar", "index": 9, "name": "warn_if", "comment": null}, "error_if": {"type": "varchar", "index": 10, "name": "error_if", "comment": null}, "test_params": {"type": "varchar", "index": 11, "name": "test_params", "comment": null}, "test_namespace": {"type": "varchar", "index": 12, "name": "test_namespace", "comment": null}, "tags": {"type": "varchar", "index": 13, "name": "tags", "comment": null}, "model_tags": {"type": "varchar", "index": 14, "name": "model_tags", "comment": null}, "model_owners": {"type": "varchar", "index": 15, "name": "model_owners", "comment": null}, "meta": {"type": "varchar", "index": 16, "name": "meta", "comment": null}, "depends_on_macros": {"type": "varchar", "index": 17, "name": "depends_on_macros", "comment": null}, "depends_on_nodes": {"type": "varchar", "index": 18, "name": "depends_on_nodes", "comment": null}, "parent_model_unique_id": {"type": "varchar", "index": 19, "name": "parent_model_unique_id", "comment": null}, "description": {"type": "varchar", "index": 20, "name": "description", "comment": null}, "package_name": {"type": "varchar", "index": 21, "name": "package_name", "comment": null}, "type": {"type": "varchar", "index": 22, "name": "type", "comment": null}, "original_path": {"type": "varchar", "index": 23, "name": "original_path", "comment": null}, "path": {"type": "varchar", "index": 24, "name": "path", "comment": null}, "generated_at": {"type": "varchar", "index": 25, "name": "generated_at", "comment": null}, "metadata_hash": {"type": "varchar", "index": 26, "name": "metadata_hash", "comment": null}, "quality_dimension": {"type": "varchar", "index": 27, "name": "quality_dimension", "comment": null}}, "stats": {"has_stats": {"id": "has_stats", "label": "Has Stats?", "value": false, "include": false, "description": "Indicates whether there are statistics for this table"}}, "unique_id": "model.elementary.dbt_tests"}, "model.data_warehouse_dbt.DimCustomer": {"metadata": {"type": "BASE TABLE", "schema": "data_marts", "name": "DimCustomer", "database": "remitpro", "comment": null, "owner": "dbo"}, "columns": {"CustomerKey": {"type": "bigint", "index": 1, "name": "CustomerKey", "comment": null}, "CustomerID": {"type": "nchar", "index": 2, "name": "CustomerID", "comment": null}, "CompanyName": {"type": "sysname", "index": 3, "name": "CompanyName", "comment": null}, "ContactName": {"type": "sysname", "index": 4, "name": "ContactName", "comment": null}, "ContactTitle": {"type": "sysname", "index": 5, "name": "ContactTitle", "comment": null}, "CustomerCountry": {"type": "sysname", "index": 6, "name": "CustomerCountry", "comment": null}, "CustomerRegion": {"type": "sysname", "index": 7, "name": "CustomerRegion", "comment": null}, "CustomerCity": {"type": "sysname", "index": 8, "name": "CustomerCity", "comment": null}, "CustomerPostalCode": {"type": "sysname", "index": 9, "name": "CustomerPostalCode", "comment": null}, "RowIsCurrent": {"type": "varchar", "index": 10, "name": "RowIsCurrent", "comment": null}, "RowStartDate": {"type": "datetime", "index": 11, "name": "RowStartDate", "comment": null}, "RowEndDate": {"type": "varchar", "index": 12, "name": "RowEndDate", "comment": null}, "RowChangeReason": {"type": "varchar", "index": 13, "name": "RowChangeReason", "comment": null}}, "stats": {"has_stats": {"id": "has_stats", "label": "Has Stats?", "value": false, "include": false, "description": "Indicates whether there are statistics for this table"}}, "unique_id": "model.data_warehouse_dbt.DimCustomer"}, "model.data_warehouse_dbt.DimEmployee": {"metadata": {"type": "BASE TABLE", "schema": "data_marts", "name": "DimEmployee", "database": "remitpro", "comment": null, "owner": "dbo"}, "columns": {"EmployeeKey": {"type": "bigint", "index": 1, "name": "EmployeeKey", "comment": null}, "EmployeeID": {"type": "int", "index": 2, "name": "EmployeeID", "comment": null}, "EmployeeName": {"type": "sysname", "index": 3, "name": "EmployeeName", "comment": null}, "EmployeeTitle": {"type": "sysname", "index": 4, "name": "EmployeeTitle", "comment": null}, "RowIsCurrent": {"type": "varchar", "index": 5, "name": "RowIsCurrent", "comment": null}, "RowStartDate": {"type": "datetime", "index": 6, "name": "RowStartDate", "comment": null}, "RowEndDate": {"type": "date", "index": 7, "name": "RowEndDate", "comment": null}, "RowChangeReason": {"type": "varchar", "index": 8, "name": "RowChangeReason", "comment": null}}, "stats": {"has_stats": {"id": "has_stats", "label": "Has Stats?", "value": false, "include": false, "description": "Indicates whether there are statistics for this table"}}, "unique_id": "model.data_warehouse_dbt.DimEmployee"}, "model.elementary.elementary_test_results": {"metadata": {"type": "BASE TABLE", "schema": "elementary", "name": "elementary_test_results", "database": "remitpro", "comment": null, "owner": "dbo"}, "columns": {"id": {"type": "varchar", "index": 1, "name": "id", "comment": null}, "data_issue_id": {"type": "varchar", "index": 2, "name": "data_issue_id", "comment": null}, "test_execution_id": {"type": "varchar", "index": 3, "name": "test_execution_id", "comment": null}, "test_unique_id": {"type": "varchar", "index": 4, "name": "test_unique_id", "comment": null}, "model_unique_id": {"type": "varchar", "index": 5, "name": "model_unique_id", "comment": null}, "invocation_id": {"type": "varchar", "index": 6, "name": "invocation_id", "comment": null}, "detected_at": {"type": "datetime2", "index": 7, "name": "detected_at", "comment": null}, "created_at": {"type": "datetime2", "index": 8, "name": "created_at", "comment": null}, "database_name": {"type": "varchar", "index": 9, "name": "database_name", "comment": null}, "schema_name": {"type": "varchar", "index": 10, "name": "schema_name", "comment": null}, "table_name": {"type": "varchar", "index": 11, "name": "table_name", "comment": null}, "column_name": {"type": "varchar", "index": 12, "name": "column_name", "comment": null}, "test_type": {"type": "varchar", "index": 13, "name": "test_type", "comment": null}, "test_sub_type": {"type": "varchar", "index": 14, "name": "test_sub_type", "comment": null}, "test_results_description": {"type": "varchar", "index": 15, "name": "test_results_description", "comment": null}, "owners": {"type": "varchar", "index": 16, "name": "owners", "comment": null}, "tags": {"type": "varchar", "index": 17, "name": "tags", "comment": null}, "test_results_query": {"type": "varchar", "index": 18, "name": "test_results_query", "comment": null}, "other": {"type": "varchar", "index": 19, "name": "other", "comment": null}, "test_name": {"type": "varchar", "index": 20, "name": "test_name", "comment": null}, "test_params": {"type": "varchar", "index": 21, "name": "test_params", "comment": null}, "severity": {"type": "varchar", "index": 22, "name": "severity", "comment": null}, "status": {"type": "varchar", "index": 23, "name": "status", "comment": null}, "failures": {"type": "bigint", "index": 24, "name": "failures", "comment": null}, "test_short_name": {"type": "varchar", "index": 25, "name": "test_short_name", "comment": null}, "test_alias": {"type": "varchar", "index": 26, "name": "test_alias", "comment": null}, "result_rows": {"type": "varchar", "index": 27, "name": "result_rows", "comment": null}, "failed_row_count": {"type": "bigint", "index": 28, "name": "failed_row_count", "comment": null}}, "stats": {"has_stats": {"id": "has_stats", "label": "Has Stats?", "value": false, "include": false, "description": "Indicates whether there are statistics for this table"}}, "unique_id": "model.elementary.elementary_test_results"}, "model.elementary.metadata": {"metadata": {"type": "BASE TABLE", "schema": "elementary", "name": "metadata", "database": "remitpro", "comment": null, "owner": "dbo"}, "columns": {"dbt_pkg_version": {"type": "varchar", "index": 1, "name": "dbt_pkg_version", "comment": null}}, "stats": {"has_stats": {"id": "has_stats", "label": "Has Stats?", "value": false, "include": false, "description": "Indicates whether there are statistics for this table"}}, "unique_id": "model.elementary.metadata"}, "model.data_warehouse_dbt.StgCategories": {"metadata": {"type": "VIEW", "schema": "staging", "name": "StgCategories", "database": "remitpro", "comment": null, "owner": "dbo"}, "columns": {"CategoryID": {"type": "int", "index": 1, "name": "CategoryID", "comment": null}, "CategoryName": {"type": "sysname", "index": 2, "name": "CategoryName", "comment": null}, "Description": {"type": "ntext", "index": 3, "name": "Description", "comment": null}, "Picture": {"type": "image", "index": 4, "name": "Picture", "comment": null}, "IngestionTimestamp": {"type": "datetime", "index": 5, "name": "IngestionTimestamp", "comment": null}}, "stats": {"has_stats": {"id": "has_stats", "label": "Has Stats?", "value": false, "include": false, "description": "Indicates whether there are statistics for this table"}}, "unique_id": "model.data_warehouse_dbt.StgCategories"}, "model.data_warehouse_dbt.StgCustomers": {"metadata": {"type": "VIEW", "schema": "staging", "name": "StgCustomers", "database": "remitpro", "comment": null, "owner": "dbo"}, "columns": {"CustomerID": {"type": "nchar", "index": 1, "name": "CustomerID", "comment": null}, "CompanyName": {"type": "sysname", "index": 2, "name": "CompanyName", "comment": null}, "ContactName": {"type": "sysname", "index": 3, "name": "ContactName", "comment": null}, "ContactTitle": {"type": "sysname", "index": 4, "name": "ContactTitle", "comment": null}, "Address": {"type": "sysname", "index": 5, "name": "Address", "comment": null}, "City": {"type": "sysname", "index": 6, "name": "City", "comment": null}, "Region": {"type": "sysname", "index": 7, "name": "Region", "comment": null}, "PostalCode": {"type": "sysname", "index": 8, "name": "PostalCode", "comment": null}, "Country": {"type": "sysname", "index": 9, "name": "Country", "comment": null}, "Phone": {"type": "sysname", "index": 10, "name": "Phone", "comment": null}, "Fax": {"type": "sysname", "index": 11, "name": "Fax", "comment": null}, "IngestionTimestamp": {"type": "datetime", "index": 12, "name": "IngestionTimestamp", "comment": null}}, "stats": {"has_stats": {"id": "has_stats", "label": "Has Stats?", "value": false, "include": false, "description": "Indicates whether there are statistics for this table"}}, "unique_id": "model.data_warehouse_dbt.StgCustomers"}, "model.data_warehouse_dbt.StgEmployees": {"metadata": {"type": "VIEW", "schema": "staging", "name": "StgEmployees", "database": "remitpro", "comment": null, "owner": "dbo"}, "columns": {"EmployeeID": {"type": "int", "index": 1, "name": "EmployeeID", "comment": null}, "LastName": {"type": "sysname", "index": 2, "name": "LastName", "comment": null}, "FirstName": {"type": "sysname", "index": 3, "name": "FirstName", "comment": null}, "Title": {"type": "sysname", "index": 4, "name": "Title", "comment": null}, "TitleOfCourtesy": {"type": "sysname", "index": 5, "name": "TitleOfCourtesy", "comment": null}, "BirthDate": {"type": "datetime", "index": 6, "name": "BirthDate", "comment": null}, "HireDate": {"type": "datetime", "index": 7, "name": "HireDate", "comment": null}, "Address": {"type": "sysname", "index": 8, "name": "Address", "comment": null}, "City": {"type": "sysname", "index": 9, "name": "City", "comment": null}, "Region": {"type": "sysname", "index": 10, "name": "Region", "comment": null}, "PostalCode": {"type": "sysname", "index": 11, "name": "PostalCode", "comment": null}, "Country": {"type": "sysname", "index": 12, "name": "Country", "comment": null}, "HomePhone": {"type": "sysname", "index": 13, "name": "HomePhone", "comment": null}, "Extension": {"type": "sysname", "index": 14, "name": "Extension", "comment": null}, "Photo": {"type": "image", "index": 15, "name": "Photo", "comment": null}, "Notes": {"type": "ntext", "index": 16, "name": "Notes", "comment": null}, "ReportsTo": {"type": "int", "index": 17, "name": "ReportsTo", "comment": null}, "PhotoPath": {"type": "sysname", "index": 18, "name": "PhotoPath", "comment": null}, "IngestionTimestamp": {"type": "datetime", "index": 19, "name": "IngestionTimestamp", "comment": null}}, "stats": {"has_stats": {"id": "has_stats", "label": "Has Stats?", "value": false, "include": false, "description": "Indicates whether there are statistics for this table"}}, "unique_id": "model.data_warehouse_dbt.StgEmployees"}, "model.data_warehouse_dbt.StgEmployeeTerritories": {"metadata": {"type": "VIEW", "schema": "staging", "name": "StgEmployeeTerritories", "database": "remitpro", "comment": null, "owner": "dbo"}, "columns": {"EmployeeID": {"type": "int", "index": 1, "name": "EmployeeID", "comment": null}, "TerritoryID": {"type": "sysname", "index": 2, "name": "TerritoryID", "comment": null}, "IngestionTimestamp": {"type": "datetime", "index": 3, "name": "IngestionTimestamp", "comment": null}}, "stats": {"has_stats": {"id": "has_stats", "label": "Has Stats?", "value": false, "include": false, "description": "Indicates whether there are statistics for this table"}}, "unique_id": "model.data_warehouse_dbt.StgEmployeeTerritories"}, "model.data_warehouse_dbt.StgOrderDetails": {"metadata": {"type": "VIEW", "schema": "staging", "name": "StgOrderDetails", "database": "remitpro", "comment": null, "owner": "dbo"}, "columns": {"OrderID": {"type": "int", "index": 1, "name": "OrderID", "comment": null}, "ProductID": {"type": "int", "index": 2, "name": "ProductID", "comment": null}, "UnitPrice": {"type": "money", "index": 3, "name": "UnitPrice", "comment": null}, "Quantity": {"type": "smallint", "index": 4, "name": "Quantity", "comment": null}, "Discount": {"type": "real", "index": 5, "name": "Discount", "comment": null}, "IngestionTimestamp": {"type": "datetime", "index": 6, "name": "IngestionTimestamp", "comment": null}}, "stats": {"has_stats": {"id": "has_stats", "label": "Has Stats?", "value": false, "include": false, "description": "Indicates whether there are statistics for this table"}}, "unique_id": "model.data_warehouse_dbt.StgOrderDetails"}, "model.data_warehouse_dbt.StgOrders": {"metadata": {"type": "VIEW", "schema": "staging", "name": "StgOrders", "database": "remitpro", "comment": null, "owner": "dbo"}, "columns": {"OrderID": {"type": "int", "index": 1, "name": "OrderID", "comment": null}, "CustomerID": {"type": "nchar", "index": 2, "name": "CustomerID", "comment": null}, "EmployeeID": {"type": "int", "index": 3, "name": "EmployeeID", "comment": null}, "OrderDate": {"type": "datetime", "index": 4, "name": "OrderDate", "comment": null}, "RequiredDate": {"type": "datetime", "index": 5, "name": "RequiredDate", "comment": null}, "ShippedDate": {"type": "datetime", "index": 6, "name": "ShippedDate", "comment": null}, "ShipVia": {"type": "int", "index": 7, "name": "ShipVia", "comment": null}, "Freight": {"type": "money", "index": 8, "name": "Freight", "comment": null}, "ShipName": {"type": "sysname", "index": 9, "name": "ShipName", "comment": null}, "ShipAddress": {"type": "sysname", "index": 10, "name": "ShipAddress", "comment": null}, "ShipCity": {"type": "sysname", "index": 11, "name": "ShipCity", "comment": null}, "ShipRegion": {"type": "sysname", "index": 12, "name": "ShipRegion", "comment": null}, "ShipPostalCode": {"type": "sysname", "index": 13, "name": "ShipPostalCode", "comment": null}, "ShipCountry": {"type": "sysname", "index": 14, "name": "ShipCountry", "comment": null}, "IngestionTimestamp": {"type": "datetime", "index": 15, "name": "IngestionTimestamp", "comment": null}}, "stats": {"has_stats": {"id": "has_stats", "label": "Has Stats?", "value": false, "include": false, "description": "Indicates whether there are statistics for this table"}}, "unique_id": "model.data_warehouse_dbt.StgOrders"}, "model.data_warehouse_dbt.StgProducts": {"metadata": {"type": "VIEW", "schema": "staging", "name": "StgProducts", "database": "remitpro", "comment": null, "owner": "dbo"}, "columns": {"ProductID": {"type": "int", "index": 1, "name": "ProductID", "comment": null}, "ProductName": {"type": "sysname", "index": 2, "name": "ProductName", "comment": null}, "SupplierID": {"type": "int", "index": 3, "name": "SupplierID", "comment": null}, "CategoryID": {"type": "int", "index": 4, "name": "CategoryID", "comment": null}, "QuantityPerUnit": {"type": "sysname", "index": 5, "name": "QuantityPerUnit", "comment": null}, "UnitPrice": {"type": "money", "index": 6, "name": "UnitPrice", "comment": null}, "UnitsInStock": {"type": "smallint", "index": 7, "name": "UnitsInStock", "comment": null}, "UnitsOnOrder": {"type": "smallint", "index": 8, "name": "UnitsOnOrder", "comment": null}, "ReorderLevel": {"type": "smallint", "index": 9, "name": "ReorderLevel", "comment": null}, "Discontinued": {"type": "bit", "index": 10, "name": "Discontinued", "comment": null}, "IngestionTimestamp": {"type": "datetime", "index": 11, "name": "IngestionTimestamp", "comment": null}}, "stats": {"has_stats": {"id": "has_stats", "label": "Has Stats?", "value": false, "include": false, "description": "Indicates whether there are statistics for this table"}}, "unique_id": "model.data_warehouse_dbt.StgProducts"}, "model.data_warehouse_dbt.StgRegion": {"metadata": {"type": "VIEW", "schema": "staging", "name": "StgRegion", "database": "remitpro", "comment": null, "owner": "dbo"}, "columns": {"RegionID": {"type": "int", "index": 1, "name": "RegionID", "comment": null}, "RegionDescription": {"type": "nchar", "index": 2, "name": "RegionDescription", "comment": null}, "IngestionTimestamp": {"type": "datetime", "index": 3, "name": "IngestionTimestamp", "comment": null}}, "stats": {"has_stats": {"id": "has_stats", "label": "Has Stats?", "value": false, "include": false, "description": "Indicates whether there are statistics for this table"}}, "unique_id": "model.data_warehouse_dbt.StgRegion"}, "model.data_warehouse_dbt.StgShippers": {"metadata": {"type": "VIEW", "schema": "staging", "name": "StgShippers", "database": "remitpro", "comment": null, "owner": "dbo"}, "columns": {"ShipperID": {"type": "int", "index": 1, "name": "ShipperID", "comment": null}, "CompanyName": {"type": "sysname", "index": 2, "name": "CompanyName", "comment": null}, "Phone": {"type": "sysname", "index": 3, "name": "Phone", "comment": null}, "IngestionTimestamp": {"type": "datetime", "index": 4, "name": "IngestionTimestamp", "comment": null}}, "stats": {"has_stats": {"id": "has_stats", "label": "Has Stats?", "value": false, "include": false, "description": "Indicates whether there are statistics for this table"}}, "unique_id": "model.data_warehouse_dbt.StgShippers"}, "model.data_warehouse_dbt.StgSuppliers": {"metadata": {"type": "VIEW", "schema": "staging", "name": "StgSuppliers", "database": "remitpro", "comment": null, "owner": "dbo"}, "columns": {"SupplierID": {"type": "int", "index": 1, "name": "SupplierID", "comment": null}, "CompanyName": {"type": "sysname", "index": 2, "name": "CompanyName", "comment": null}, "ContactName": {"type": "sysname", "index": 3, "name": "ContactName", "comment": null}, "ContactTitle": {"type": "sysname", "index": 4, "name": "ContactTitle", "comment": null}, "Address": {"type": "sysname", "index": 5, "name": "Address", "comment": null}, "City": {"type": "sysname", "index": 6, "name": "City", "comment": null}, "Region": {"type": "sysname", "index": 7, "name": "Region", "comment": null}, "PostalCode": {"type": "sysname", "index": 8, "name": "PostalCode", "comment": null}, "Country": {"type": "sysname", "index": 9, "name": "Country", "comment": null}, "Phone": {"type": "sysname", "index": 10, "name": "Phone", "comment": null}, "Fax": {"type": "sysname", "index": 11, "name": "Fax", "comment": null}, "HomePage": {"type": "ntext", "index": 12, "name": "HomePage", "comment": null}, "IngestionTimestamp": {"type": "datetime", "index": 13, "name": "IngestionTimestamp", "comment": null}}, "stats": {"has_stats": {"id": "has_stats", "label": "Has Stats?", "value": false, "include": false, "description": "Indicates whether there are statistics for this table"}}, "unique_id": "model.data_warehouse_dbt.StgSuppliers"}, "model.data_warehouse_dbt.StgTerritories": {"metadata": {"type": "VIEW", "schema": "staging", "name": "StgTerritories", "database": "remitpro", "comment": null, "owner": "dbo"}, "columns": {"TerritoryID": {"type": "sysname", "index": 1, "name": "TerritoryID", "comment": null}, "TerritoryDescription": {"type": "nchar", "index": 2, "name": "TerritoryDescription", "comment": null}, "RegionID": {"type": "int", "index": 3, "name": "RegionID", "comment": null}, "IngestionTimestamp": {"type": "datetime", "index": 4, "name": "IngestionTimestamp", "comment": null}}, "stats": {"has_stats": {"id": "has_stats", "label": "Has Stats?", "value": false, "include": false, "description": "Indicates whether there are statistics for this table"}}, "unique_id": "model.data_warehouse_dbt.StgTerritories"}, "model.elementary.test_result_rows": {"metadata": {"type": "BASE TABLE", "schema": "elementary", "name": "test_result_rows", "database": "remitpro", "comment": null, "owner": "dbo"}, "columns": {"elementary_test_results_id": {"type": "varchar", "index": 1, "name": "elementary_test_results_id", "comment": null}, "result_row": {"type": "varchar", "index": 2, "name": "result_row", "comment": null}, "detected_at": {"type": "datetime2", "index": 3, "name": "detected_at", "comment": null}, "created_at": {"type": "datetime2", "index": 4, "name": "created_at", "comment": null}}, "stats": {"has_stats": {"id": "has_stats", "label": "Has Stats?", "value": false, "include": false, "description": "Indicates whether there are statistics for this table"}}, "unique_id": "model.elementary.test_result_rows"}}, "sources": {"source.data_warehouse_dbt.northwind.Categories": {"metadata": {"type": "BASE TABLE", "schema": "dbo", "name": "Categories", "database": "remitpro", "comment": null, "owner": "dbo"}, "columns": {"CategoryID": {"type": "int", "index": 1, "name": "CategoryID", "comment": null}, "CategoryName": {"type": "sysname", "index": 2, "name": "CategoryName", "comment": null}, "Description": {"type": "ntext", "index": 3, "name": "Description", "comment": null}, "Picture": {"type": "image", "index": 4, "name": "Picture", "comment": null}}, "stats": {"has_stats": {"id": "has_stats", "label": "Has Stats?", "value": false, "include": false, "description": "Indicates whether there are statistics for this table"}}, "unique_id": "source.data_warehouse_dbt.northwind.Categories"}, "source.data_warehouse_dbt.northwind.CustomerDemographics": {"metadata": {"type": "BASE TABLE", "schema": "dbo", "name": "CustomerDemographics", "database": "remitpro", "comment": null, "owner": "dbo"}, "columns": {"CustomerTypeID": {"type": "nchar", "index": 1, "name": "CustomerTypeID", "comment": null}, "CustomerDesc": {"type": "ntext", "index": 2, "name": "CustomerDesc", "comment": null}}, "stats": {"has_stats": {"id": "has_stats", "label": "Has Stats?", "value": false, "include": false, "description": "Indicates whether there are statistics for this table"}}, "unique_id": "source.data_warehouse_dbt.northwind.CustomerDemographics"}, "source.data_warehouse_dbt.northwind.Customers": {"metadata": {"type": "BASE TABLE", "schema": "dbo", "name": "Customers", "database": "remitpro", "comment": null, "owner": "dbo"}, "columns": {"CustomerID": {"type": "nchar", "index": 1, "name": "CustomerID", "comment": null}, "CompanyName": {"type": "sysname", "index": 2, "name": "CompanyName", "comment": null}, "ContactName": {"type": "sysname", "index": 3, "name": "ContactName", "comment": null}, "ContactTitle": {"type": "sysname", "index": 4, "name": "ContactTitle", "comment": null}, "Address": {"type": "sysname", "index": 5, "name": "Address", "comment": null}, "City": {"type": "sysname", "index": 6, "name": "City", "comment": null}, "Region": {"type": "sysname", "index": 7, "name": "Region", "comment": null}, "PostalCode": {"type": "sysname", "index": 8, "name": "PostalCode", "comment": null}, "Country": {"type": "sysname", "index": 9, "name": "Country", "comment": null}, "Phone": {"type": "sysname", "index": 10, "name": "Phone", "comment": null}, "Fax": {"type": "sysname", "index": 11, "name": "Fax", "comment": null}}, "stats": {"has_stats": {"id": "has_stats", "label": "Has Stats?", "value": false, "include": false, "description": "Indicates whether there are statistics for this table"}}, "unique_id": "source.data_warehouse_dbt.northwind.Customers"}, "source.data_warehouse_dbt.northwind.Employees": {"metadata": {"type": "BASE TABLE", "schema": "dbo", "name": "Employees", "database": "remitpro", "comment": null, "owner": "dbo"}, "columns": {"EmployeeID": {"type": "int", "index": 1, "name": "EmployeeID", "comment": null}, "LastName": {"type": "sysname", "index": 2, "name": "LastName", "comment": null}, "FirstName": {"type": "sysname", "index": 3, "name": "FirstName", "comment": null}, "Title": {"type": "sysname", "index": 4, "name": "Title", "comment": null}, "TitleOfCourtesy": {"type": "sysname", "index": 5, "name": "TitleOfCourtesy", "comment": null}, "BirthDate": {"type": "datetime", "index": 6, "name": "BirthDate", "comment": null}, "HireDate": {"type": "datetime", "index": 7, "name": "HireDate", "comment": null}, "Address": {"type": "sysname", "index": 8, "name": "Address", "comment": null}, "City": {"type": "sysname", "index": 9, "name": "City", "comment": null}, "Region": {"type": "sysname", "index": 10, "name": "Region", "comment": null}, "PostalCode": {"type": "sysname", "index": 11, "name": "PostalCode", "comment": null}, "Country": {"type": "sysname", "index": 12, "name": "Country", "comment": null}, "HomePhone": {"type": "sysname", "index": 13, "name": "HomePhone", "comment": null}, "Extension": {"type": "sysname", "index": 14, "name": "Extension", "comment": null}, "Photo": {"type": "image", "index": 15, "name": "Photo", "comment": null}, "Notes": {"type": "ntext", "index": 16, "name": "Notes", "comment": null}, "ReportsTo": {"type": "int", "index": 17, "name": "ReportsTo", "comment": null}, "PhotoPath": {"type": "sysname", "index": 18, "name": "PhotoPath", "comment": null}}, "stats": {"has_stats": {"id": "has_stats", "label": "Has Stats?", "value": false, "include": false, "description": "Indicates whether there are statistics for this table"}}, "unique_id": "source.data_warehouse_dbt.northwind.Employees"}, "source.data_warehouse_dbt.northwind.EmployeeTerritories": {"metadata": {"type": "BASE TABLE", "schema": "dbo", "name": "EmployeeTerritories", "database": "remitpro", "comment": null, "owner": "dbo"}, "columns": {"EmployeeID": {"type": "int", "index": 1, "name": "EmployeeID", "comment": null}, "TerritoryID": {"type": "sysname", "index": 2, "name": "TerritoryID", "comment": null}}, "stats": {"has_stats": {"id": "has_stats", "label": "Has Stats?", "value": false, "include": false, "description": "Indicates whether there are statistics for this table"}}, "unique_id": "source.data_warehouse_dbt.northwind.EmployeeTerritories"}, "source.data_warehouse_dbt.northwind.Invoices": {"metadata": {"type": "VIEW", "schema": "dbo", "name": "Invoices", "database": "remitpro", "comment": null, "owner": "dbo"}, "columns": {"ShipName": {"type": "sysname", "index": 1, "name": "ShipName", "comment": null}, "ShipAddress": {"type": "sysname", "index": 2, "name": "ShipAddress", "comment": null}, "ShipCity": {"type": "sysname", "index": 3, "name": "ShipCity", "comment": null}, "ShipRegion": {"type": "sysname", "index": 4, "name": "ShipRegion", "comment": null}, "ShipPostalCode": {"type": "sysname", "index": 5, "name": "ShipPostalCode", "comment": null}, "ShipCountry": {"type": "sysname", "index": 6, "name": "ShipCountry", "comment": null}, "CustomerID": {"type": "nchar", "index": 7, "name": "CustomerID", "comment": null}, "CustomerName": {"type": "sysname", "index": 8, "name": "CustomerName", "comment": null}, "Address": {"type": "sysname", "index": 9, "name": "Address", "comment": null}, "City": {"type": "sysname", "index": 10, "name": "City", "comment": null}, "Region": {"type": "sysname", "index": 11, "name": "Region", "comment": null}, "PostalCode": {"type": "sysname", "index": 12, "name": "PostalCode", "comment": null}, "Country": {"type": "sysname", "index": 13, "name": "Country", "comment": null}, "Salesperson": {"type": "sysname", "index": 14, "name": "Salesperson", "comment": null}, "OrderID": {"type": "int", "index": 15, "name": "OrderID", "comment": null}, "OrderDate": {"type": "datetime", "index": 16, "name": "OrderDate", "comment": null}, "RequiredDate": {"type": "datetime", "index": 17, "name": "RequiredDate", "comment": null}, "ShippedDate": {"type": "datetime", "index": 18, "name": "ShippedDate", "comment": null}, "ShipperName": {"type": "sysname", "index": 19, "name": "ShipperName", "comment": null}, "ProductID": {"type": "int", "index": 20, "name": "ProductID", "comment": null}, "ProductName": {"type": "sysname", "index": 21, "name": "ProductName", "comment": null}, "UnitPrice": {"type": "money", "index": 22, "name": "UnitPrice", "comment": null}, "Quantity": {"type": "smallint", "index": 23, "name": "Quantity", "comment": null}, "Discount": {"type": "real", "index": 24, "name": "Discount", "comment": null}, "ExtendedPrice": {"type": "money", "index": 25, "name": "ExtendedPrice", "comment": null}, "Freight": {"type": "money", "index": 26, "name": "Freight", "comment": null}}, "stats": {"has_stats": {"id": "has_stats", "label": "Has Stats?", "value": false, "include": false, "description": "Indicates whether there are statistics for this table"}}, "unique_id": "source.data_warehouse_dbt.northwind.Invoices"}, "source.data_warehouse_dbt.northwind.Order Details": {"metadata": {"type": "BASE TABLE", "schema": "dbo", "name": "Order Details", "database": "remitpro", "comment": null, "owner": "dbo"}, "columns": {"OrderID": {"type": "int", "index": 1, "name": "OrderID", "comment": null}, "ProductID": {"type": "int", "index": 2, "name": "ProductID", "comment": null}, "UnitPrice": {"type": "money", "index": 3, "name": "UnitPrice", "comment": null}, "Quantity": {"type": "smallint", "index": 4, "name": "Quantity", "comment": null}, "Discount": {"type": "real", "index": 5, "name": "Discount", "comment": null}}, "stats": {"has_stats": {"id": "has_stats", "label": "Has Stats?", "value": false, "include": false, "description": "Indicates whether there are statistics for this table"}}, "unique_id": "source.data_warehouse_dbt.northwind.Order Details"}, "source.data_warehouse_dbt.northwind.Orders": {"metadata": {"type": "BASE TABLE", "schema": "dbo", "name": "Orders", "database": "remitpro", "comment": null, "owner": "dbo"}, "columns": {"OrderID": {"type": "int", "index": 1, "name": "OrderID", "comment": null}, "CustomerID": {"type": "nchar", "index": 2, "name": "CustomerID", "comment": null}, "EmployeeID": {"type": "int", "index": 3, "name": "EmployeeID", "comment": null}, "OrderDate": {"type": "datetime", "index": 4, "name": "OrderDate", "comment": null}, "RequiredDate": {"type": "datetime", "index": 5, "name": "RequiredDate", "comment": null}, "ShippedDate": {"type": "datetime", "index": 6, "name": "ShippedDate", "comment": null}, "ShipVia": {"type": "int", "index": 7, "name": "ShipVia", "comment": null}, "Freight": {"type": "money", "index": 8, "name": "Freight", "comment": null}, "ShipName": {"type": "sysname", "index": 9, "name": "ShipName", "comment": null}, "ShipAddress": {"type": "sysname", "index": 10, "name": "ShipAddress", "comment": null}, "ShipCity": {"type": "sysname", "index": 11, "name": "ShipCity", "comment": null}, "ShipRegion": {"type": "sysname", "index": 12, "name": "ShipRegion", "comment": null}, "ShipPostalCode": {"type": "sysname", "index": 13, "name": "ShipPostalCode", "comment": null}, "ShipCountry": {"type": "sysname", "index": 14, "name": "ShipCountry", "comment": null}}, "stats": {"has_stats": {"id": "has_stats", "label": "Has Stats?", "value": false, "include": false, "description": "Indicates whether there are statistics for this table"}}, "unique_id": "source.data_warehouse_dbt.northwind.Orders"}, "source.data_warehouse_dbt.northwind.Products": {"metadata": {"type": "BASE TABLE", "schema": "dbo", "name": "Products", "database": "remitpro", "comment": null, "owner": "dbo"}, "columns": {"ProductID": {"type": "int", "index": 1, "name": "ProductID", "comment": null}, "ProductName": {"type": "sysname", "index": 2, "name": "ProductName", "comment": null}, "SupplierID": {"type": "int", "index": 3, "name": "SupplierID", "comment": null}, "CategoryID": {"type": "int", "index": 4, "name": "CategoryID", "comment": null}, "QuantityPerUnit": {"type": "sysname", "index": 5, "name": "QuantityPerUnit", "comment": null}, "UnitPrice": {"type": "money", "index": 6, "name": "UnitPrice", "comment": null}, "UnitsInStock": {"type": "smallint", "index": 7, "name": "UnitsInStock", "comment": null}, "UnitsOnOrder": {"type": "smallint", "index": 8, "name": "UnitsOnOrder", "comment": null}, "ReorderLevel": {"type": "smallint", "index": 9, "name": "ReorderLevel", "comment": null}, "Discontinued": {"type": "bit", "index": 10, "name": "Discontinued", "comment": null}}, "stats": {"has_stats": {"id": "has_stats", "label": "Has Stats?", "value": false, "include": false, "description": "Indicates whether there are statistics for this table"}}, "unique_id": "source.data_warehouse_dbt.northwind.Products"}, "source.data_warehouse_dbt.northwind.Region": {"metadata": {"type": "BASE TABLE", "schema": "dbo", "name": "Region", "database": "remitpro", "comment": null, "owner": "dbo"}, "columns": {"RegionID": {"type": "int", "index": 1, "name": "RegionID", "comment": null}, "RegionDescription": {"type": "nchar", "index": 2, "name": "RegionDescription", "comment": null}}, "stats": {"has_stats": {"id": "has_stats", "label": "Has Stats?", "value": false, "include": false, "description": "Indicates whether there are statistics for this table"}}, "unique_id": "source.data_warehouse_dbt.northwind.Region"}, "source.data_warehouse_dbt.northwind.Shippers": {"metadata": {"type": "BASE TABLE", "schema": "dbo", "name": "Shippers", "database": "remitpro", "comment": null, "owner": "dbo"}, "columns": {"ShipperID": {"type": "int", "index": 1, "name": "ShipperID", "comment": null}, "CompanyName": {"type": "sysname", "index": 2, "name": "CompanyName", "comment": null}, "Phone": {"type": "sysname", "index": 3, "name": "Phone", "comment": null}}, "stats": {"has_stats": {"id": "has_stats", "label": "Has Stats?", "value": false, "include": false, "description": "Indicates whether there are statistics for this table"}}, "unique_id": "source.data_warehouse_dbt.northwind.Shippers"}, "source.data_warehouse_dbt.northwind.Suppliers": {"metadata": {"type": "BASE TABLE", "schema": "dbo", "name": "Suppliers", "database": "remitpro", "comment": null, "owner": "dbo"}, "columns": {"SupplierID": {"type": "int", "index": 1, "name": "SupplierID", "comment": null}, "CompanyName": {"type": "sysname", "index": 2, "name": "CompanyName", "comment": null}, "ContactName": {"type": "sysname", "index": 3, "name": "ContactName", "comment": null}, "ContactTitle": {"type": "sysname", "index": 4, "name": "ContactTitle", "comment": null}, "Address": {"type": "sysname", "index": 5, "name": "Address", "comment": null}, "City": {"type": "sysname", "index": 6, "name": "City", "comment": null}, "Region": {"type": "sysname", "index": 7, "name": "Region", "comment": null}, "PostalCode": {"type": "sysname", "index": 8, "name": "PostalCode", "comment": null}, "Country": {"type": "sysname", "index": 9, "name": "Country", "comment": null}, "Phone": {"type": "sysname", "index": 10, "name": "Phone", "comment": null}, "Fax": {"type": "sysname", "index": 11, "name": "Fax", "comment": null}, "HomePage": {"type": "ntext", "index": 12, "name": "HomePage", "comment": null}}, "stats": {"has_stats": {"id": "has_stats", "label": "Has Stats?", "value": false, "include": false, "description": "Indicates whether there are statistics for this table"}}, "unique_id": "source.data_warehouse_dbt.northwind.Suppliers"}, "source.data_warehouse_dbt.northwind.Territories": {"metadata": {"type": "BASE TABLE", "schema": "dbo", "name": "Territories", "database": "remitpro", "comment": null, "owner": "dbo"}, "columns": {"TerritoryID": {"type": "sysname", "index": 1, "name": "TerritoryID", "comment": null}, "TerritoryDescription": {"type": "nchar", "index": 2, "name": "TerritoryDescription", "comment": null}, "RegionID": {"type": "int", "index": 3, "name": "RegionID", "comment": null}}, "stats": {"has_stats": {"id": "has_stats", "label": "Has Stats?", "value": false, "include": false, "description": "Indicates whether there are statistics for this table"}}, "unique_id": "source.data_warehouse_dbt.northwind.Territories"}}, "errors": null}